{
    "datatypes": {
        "answers": {
            "datatypes1": "int",
            "datatypes2": "float",
            "datatypes3": "str",
            "datatypes4": "list"
        },
        "score": 1
    },
    "operators": {
        "answers": {
            "Operators1": 24,
            "Operators2": 13.23,
            "Operators3": 123123,
            "Operators4": 2,
            "Operators5": "bca"
        },
        "score": 1
    },
    "variables": {
        "answers": {
            "Variables1a": 20,
            "Variables1b": 20,
            "Variables2a": 10,
            "Variables2b": 10,
            "Variables3a": 20,
            "Variables3b": 20,
            "Variables4a": 10,
            "Variables4b": 10,
            "Variables5a": 20,
            "Variables5b": 30,
            "Variables5c": 30,
            "Variables6a": 30,
            "Variables6b": 30,
            "Variables6c": 30
        },
        "score": 1
    },
    "bool": {
        "answers": {
            "100 == 100": "True",
            "2 > 7": "False",
            "(10 + 3) >= 13": "True",
            "(10*2) < 9": "False",
            "(1 + 3) < (2*3)": "True",
            "(10.3 + 9) == (10.3 + 10)": "False",
            "100 != 100": "False",
            "(5 < 7) and (4 > 5)": "False",
            "(5 < 7) or (4 > 5)": "True",
            "(3 < 7) and (7 < 9)": "True",
            "(3 < 7) or (7 < 9)": "True",
            "not (100 != 100)": "True",
            "True != True": "False",
            "True and False": "False",
            "True or False": "True",
            "True and True": "True",
            "True or True": "True",
            "not (True != True)": "True",
            "n < 10": "True",
            "100 == n": "False",
            "(n < 7) and (4 > n)": "False",
            "(n < 7) or (4 > n)": "True",
            "n <= 5": "True",
            "not (n < 10)": "False"
        },
        "score": 0.2
    },
    "conditionals": {
        "answers": {
            "Conditionals1": "Ingenting",
            "Conditionals2": 2,
            "Conditionals3": 2,
            "Conditionals4": "1 og 2"            
        },
        "score": 1
    },
    "loops": {
        "answers": {
            "Loops1": 10,
            "Loops2": 10,
            "Loops3": 100,
            "Loops4": 4,
            "Loops5": 5,
            "Loops6": 9,
            "Loops7": "xbdac"            
        },
        "score": 1
    },
    "lists": {
        "answers": {
            "Lists1": 20,
            "Lists2": 25,
            "Lists3a": "[10, 20, 30]",
            "Lists3b": "[5, 35, 25]"
        },
        "score": 1
    },
    "functions": {
        "answers": {
            "Functions1": 15,
            "Functions2": 1,
            "Functions3": 1,
            "Functions4": 5,
            "Functions5": 10,
            "Functions6": "abcxyz",
            "Functions7": "c",
            "Functions8": 25,
            "Functions9": 90
        },
        "score": 1
    }
}